{
  "color": {
        "primitive": {
            "black": {
                "100": { "value": "#DDE1E6" },
                "200": { "value": "#CAD1D9" },
                "300": { "value": "#B8C2CC" },
                "400": { "value": "#8B959E" },
                "500": { "value": "#626A73" },
                "600": { "value": "#4E555C" },
                "700": { "value": "#40464C" },
                "800": { "value": "#212326" },
                "900": { "value": "#000000" }
                },      

            "white": {
                "base": { "value": "#FFFFFF" },
                "opacity": {
                    "05": { "value": "rgba(255, 255, 255, 0.05)" },
                    "10": { "value": "rgba(255, 255, 255, 0.1)" },
                    "25": { "value": "rgba(255, 255, 255, 0.25)" },
                    "50": { "value": "rgba(255, 255, 255, 0.5)" },
                    "75": { "value": "rgba(255, 255, 255, 0.75)" },
                    "100": { "value": "rgba(255, 255, 255, 1)"}
                }
            }, 

            "light": {
                "red": {
                    "100": { "value": "#FBE5E8" },
                    "200": { "value": "#F7BFC6" },
                    "300": { "value": "#EF808D" },
                    "400": { "value": "#E84155" },
                    "500": { "value": "#E0011C" },
                    "600": { "value": "#CA0119" },
                    "700": { "value": "#B30116" },
                    "800": { "value": "#9D0114" },
                    "900": { "value": "#860111" }
                }, 

                "green": {
                    "100": { "value": "#E5F6E5" },
                    "200": { "value": "#C4E3CD" },
                    "300": { "value": "#89C89A" },
                    "400": { "value": "#4EAD69" },
                    "500": { "value": "#139136" },
                    "600": { "value": "#118231" },
                    "700": { "value": "#0F742B" },
                    "800": { "value": "#0D6626" },
                    "900": { "value": "#0B5720" }
                },

                "orange": {
                    "100": { "value": "#FDEEE5" },
                    "200": { "value": "#FBD5BF" },
                    "300": { "value": "#F7AB7F" },
                    "400": { "value": "#F48140" },
                    "500": { "value": "#F05700" },
                    "600": { "value": "#D84E00" },
                    "700": { "value": "#C04600" },
                    "800": { "value": "#903400" },
                    "900": { "value": "#782C00" }
                }
            },
            
            "dark": {
                "red": {
                    "100": { "value": "#531F30" },
                    "200": { "value": "#8C293C" },
                    "300": { "value": "#C53247" },
                    "400": { "value": "#E5354A" },
                    "500": { "value": "#FE3B52" },
                    "600": { "value": "#E92C43" },
                    "700": { "value": "#D31E34" },
                    "800": { "value": "#BE0F24" },
                    "900": { "value": "#A90015" }
                }, 

                "green": {
                    "100": { "value": "#2A4732" },
                    "200": { "value": "#397940" },
                    "300": { "value": "#49AA4D" },
                    "400": { "value": "#4FC551" },
                    "500": { "value": "#58DB5A" },
                    "600": { "value": "#42BD4A" },
                    "700": { "value": "#2C9F3B" },
                    "800": { "value": "#16812B" },
                    "900": { "value": "#00631B" }
                },

                "orange": {
                    "100": { "value": "#532C22" },
                    "200": { "value": "#8C411F" },
                    "300": { "value": "#C6571C" },
                    "400": { "value": "#E56117" },
                    "500": { "value": "#FF6C19" },
                    "600": { "value": "#E35B13" },
                    "700": { "value": "#C7490D" },
                    "800": { "value": "#AC3806" },
                    "900": { "value": "#902600" }
                }
            } 
        }
    }
}
